midea_beautiful/__init__.py
midea_beautiful/appliance.py
midea_beautiful/cli.py
midea_beautiful/cloud.py
midea_beautiful/command.py
midea_beautiful/crypto.py
midea_beautiful/exceptions.py
midea_beautiful/lan.py
midea_beautiful/midea.py
midea_beautiful/scanner.py
midea_beautiful/util.py
midea_beautiful/version.py
midea_beautiful_air-0.10.5.dist-info/LICENSE
midea_beautiful_air-0.10.5.dist-info/METADATA
midea_beautiful_air-0.10.5.dist-info/WHEEL
midea_beautiful_air-0.10.5.dist-info/entry_points.txt
midea_beautiful_air-0.10.5.dist-info/top_level.txt
midea_beautiful_air-0.10.5.dist-info/RECORD
