Metadata-Version: 2.1
Name: midea-beautiful-air
Version: 0.10.5
Summary: A library to control Midea appliances via the local network
Home-page: https://github.com/nbogojevic/midea-beautiful-air
Author: Nenad Bogojević
Author-email: nenad.bogojevic@gmail.com
License: MIT
Classifier: Intended Audience :: Developers
Classifier: License :: OSI Approved :: MIT License
Classifier: Operating System :: MacOS :: MacOS X
Classifier: Operating System :: Microsoft :: Windows
Classifier: Operating System :: POSIX :: Linux
Classifier: Programming Language :: Python :: 3
Classifier: Topic :: Home Automation
Requires-Python: >=3.8
License-File: LICENSE
Requires-Dist: cryptography >=3.0
Requires-Dist: requests >=2.0
